<?xml version="1.0" encoding="iso-8859-1"?>

<userOverrides>
  <override>
    <path>E:\Git_repository\ST_UD01\BSP\UART_Drv.c</path>
    <encoding>System</encoding>
  </override>
  <override>
    <path>E:\Git_repository\ST_UD01\temp\Ymodem_x.c</path>
    <encoding>System</encoding>
  </override>
  <override>
    <path>E:\Git_repository\ST_UD01\user\main.c</path>
    <encoding>System</encoding>
  </override>
  <override>
    <path>E:\Git_repository\ST_UD01_V1.0\BSP\LED.c</path>
    <encoding>UTF-8</encoding>
  </override>
  <override>
    <path>E:\Git_repository\ST_UD01_V1.0\BSP\UART_Drv.c</path>
    <encoding>UTF-8</encoding>
  </override>
  <override>
    <path>E:\Git_repository\ST_UD01_V1.0\BSP\UART_Drv.h</path>
    <encoding>UTF-8</encoding>
  </override>
  <override>
    <path>E:\Git_repository\ST_UD01_V1.0\BSP\button.c</path>
    <encoding>UTF-8</encoding>
  </override>
  <override>
    <path>E:\Git_repository\ST_UD01_V1.0\boot\IAP.c</path>
    <encoding>UTF-8</encoding>
  </override>
  <override>
    <path>E:\Git_repository\ST_UD01_V1.0\boot\Ymodem.c</path>
    <encoding>UTF-8</encoding>
  </override>
  <override>
    <path>E:\Git_repository\ST_UD01_V1.0\user\def_and_type.h</path>
    <encoding>UTF-8</encoding>
  </override>
  <override>
    <path>E:\Git_repository\ST_UD01_V1.0\user\main.c</path>
    <encoding>UTF-8</encoding>
  </override>
</userOverrides>


